openimu/__init__.py
openimu/__main__.py
openimu/bootloader_input_packet.py
openimu/commands.py
openimu/file_storage.py
openimu/global_vars.py
openimu/imu_input_packet.py
openimu/openimu.py
openimu/server.py
openimu/app_config/Compass/openimu.json
openimu/app_config/IMU/openimu.json
openimu/app_config/INS/openimu.json
openimu/app_config/Leveler/openimu.json
openimu/app_config/VG_AHRS/openimu.json
openimu_testa-0.0.1.data/data/openimu.json
openimu_testa-0.0.1.dist-info/LICENSE
openimu_testa-0.0.1.dist-info/METADATA
openimu_testa-0.0.1.dist-info/WHEEL
openimu_testa-0.0.1.dist-info/entry_points.txt
openimu_testa-0.0.1.dist-info/top_level.txt
openimu_testa-0.0.1.dist-info/RECORD
